bluetooth/__init__.py
bluetooth/__init__.pyi
btree/__init__.py
btree/__init__.pyi
cryptolib/__init__.py
cryptolib/__init__.pyi
esp/__init__.py
esp/__init__.pyi
esp32/__init__.py
esp32/__init__.pyi
framebuf/__init__.py
framebuf/__init__.pyi
lcd160cr/__init__.py
lcd160cr/__init__.pyi
machine/ADCWiPy.pyi
machine/TimerWiPy.pyi
machine/__init__.py
machine/__init__.pyi
micropython/__init__.py
micropython/__init__.pyi
neopixel/__init__.py
neopixel/__init__.pyi
network/__init__.py
network/__init__.pyi
pyb/__init__.py
pyb/__init__.pyi
rp2/__init__.py
stm/__init__.py
stm/__init__.pyi
uarray/__init__.py
uarray/__init__.pyi
uasyncio/__init__.py
uasyncio/__init__.pyi
ubinascii/__init__.py
ubinascii/__init__.pyi
ubluetooth/__init__.py
ubluetooth/__init__.pyi
ucollections/__init__.py
ucollections/__init__.pyi
ucryptolib/__init__.py
ucryptolib/__init__.pyi
uctypes/__init__.py
uctypes/__init__.pyi
uerrno/__init__.py
uerrno/__init__.pyi
uhashlib/__init__.py
uhashlib/__init__.pyi
uheapq/__init__.py
uheapq/__init__.pyi
uio/__init__.py
uio/__init__.pyi
ujson/__init__.py
ujson/__init__.pyi
uos/__init__.py
uos/__init__.pyi
ure/__init__.py
ure/__init__.pyi
urequests/__init__.py
urequests/__init__.pyi
uselect/__init__.py
uselect/__init__.pyi
usocket/__init__.py
usocket/__init__.pyi
ussl/__init__.py
ussl/__init__.pyi
ustruct/__init__.py
ustruct/__init__.pyi
usys/__init__.py
usys/__init__.pyi
utime/__init__.py
utime/__init__.pyi
uzlib/__init__.py
uzlib/__init__.pyi
wipy/__init__.py
wipy/__init__.pyi
zephyr/__init__.py
huas_micropython-0.0.2.dist-info/LICENSE
huas_micropython-0.0.2.dist-info/METADATA
huas_micropython-0.0.2.dist-info/WHEEL
huas_micropython-0.0.2.dist-info/top_level.txt
huas_micropython-0.0.2.dist-info/zip-safe
huas_micropython-0.0.2.dist-info/RECORD
