Metadata-Version: 2.1
Name: huas-micropython
Version: 0.0.2
Summary: Micropython stub files and dependencies
Home-page: https://github.com/misja/huas-micropython
Author: Misja Hoebe
Author-email: m.n.hoebe@pl.hanze.nl
License: MIT
Project-URL: Source, https://github.com/misja/huas-micropython
Project-URL: Tracker, https://github.com/misja/huas-micropython/issues
Keywords: micropython,stubs
Platform: UNKNOWN
Classifier: Typing :: Typed
Classifier: Intended Audience :: Developers
Classifier: Operating System :: OS Independent
Classifier: License :: OSI Approved :: MIT License
Classifier: Programming Language :: Python :: Implementation :: MicroPython
Requires-Python: >=3.8
License-File: LICENSE
Provides-Extra: all
Requires-Dist: adafruit-ampy ; extra == 'all'
Requires-Dist: esptool ; extra == 'all'
